pygpgme-0.6.dist-info/top_level.txt
pygpgme-0.6.dist-info/RECORD
pygpgme-0.6.dist-info/LICENSE.txt
pygpgme-0.6.dist-info/METADATA
pygpgme-0.6.dist-info/WHEEL
gpgme/__init__.py
gpgme/_gpgme.cpython-39-x86_64-linux-gnu.so
gpgme/_gpgme.pyi
gpgme/editutil.py
gpgme/py.typed
pygpgme.libs/libgpg-error-d4e115d0.so.0.24.2
pygpgme.libs/libassuan-7259bce6.so.0.8.1
pygpgme.libs/libgpgme-c2876b78.so.11.22.1
