Metadata-Version: 2.1
Name: pygpgme
Version: 0.6
Summary: A Python module for working with OpenPGP messages
Author-email: James Henstridge <james@jamesh.id.au>
License: 		  GNU LESSER GENERAL PUBLIC LICENSE
Project-URL: Repository, https://github.com/jhenstridge/pygpgme
Project-URL: Documentation, https://pygpgme.readthedocs.io
Classifier: Intended Audience :: Developers
Classifier: License :: OSI Approved :: GNU Lesser General Public License v2 or later (LGPLv2+)
Classifier: Operating System :: POSIX
Classifier: Programming Language :: C
Classifier: Programming Language :: Python :: 3
Classifier: Topic :: Security :: Cryptography
Classifier: Topic :: Software Development :: Libraries :: Python Modules
Requires-Python: >=3.9
License-File: LICENSE.txt
Requires-Dist: typing_extensions; python_version < "3.10"
Provides-Extra: docs
Requires-Dist: Sphinx; extra == "docs"
Requires-Dist: sphinx-rtd-theme; extra == "docs"
